Workbook

Sheet Assumptions
A1: Promotion Scenario Model - Assumptions
A2: Yellow cells are inputs. The Scenario Model sheet is entirely formula-driven.
A4: Assumption | B4: Value | C4: Note
A5: Cashback rate | B5: 0.03 | C5: Cashback paid to cardholder on eligible spend
A6: Contribution margin on incremental spend | B6: 0.25 | C6: Rate at which incremental revenue becomes profit
A7: Merchant funding share of cashback | B7: 1 | C7: 1.0 = merchant pays the entire cashback bill
A8: Targeted population (customers) | B8: 252750 | C8: Rollout base x targeted share (34%); segments: Affluent Frequent, Digital Native
A9: Promo windows per year | B9: 4 | C9: Number of 12-week promotion windows run annually
A10: Counterfactual eligible spend / customer / window | B10: 556.33199 | C10: Dining+Entertainment spend WITHOUT the promo (from DiD)
A11: Promotion cost / customer / window | B11: 20.321086 | C11: Actual cashback paid per treated customer in the pilot
A12: Incremental eligible spend / cust / window - CONSERVATIVE | B12: 74.070627 | C12: Lower bound of the 95% CI on the DiD estimate
A13: Incremental eligible spend / cust / window - BASE | B13: 121.03238 | C13: DiD point estimate
A14: Incremental eligible spend / cust / window - UPSIDE | B14: 167.99413 | C14: Upper bound of the 95% CI on the DiD estimate
A15: Halo spend / customer / window (non-eligible categories) | B15: 85.119465 | C15: Extra spend outside Dining+Entertainment - upside only, not in headline ROI

Sheet Scenario Model
A1: Annual Promotion Economics by Scenario
A3: Metric | B3: Conservative | C3: Base | D3: Upside
A4: Incremental eligible spend / customer / window | B4: =Assumptions!$B$12 -> 0 | C4: =Assumptions!$B$13 -> 0 | D4: =Assumptions!$B$14 -> 0
A5: Targeted population | B5: =Assumptions!$B$8 -> 0 | C5: =Assumptions!$B$8 -> 0 | D5: =Assumptions!$B$8 -> 0
A6: Promo windows per year | B6: =Assumptions!$B$9 -> 0 | C6: =Assumptions!$B$9 -> 0 | D6: =Assumptions!$B$9 -> 0
A7: Annual incremental eligible spend | B7: =B4*B5*B6 -> 0 | C7: =C4*C5*C6 -> 0 | D7: =D4*D5*D6 -> 0
A8: Annual promotion cost | B8: =Assumptions!$B$11*B5*B6 -> 0 | C8: =Assumptions!$B$11*C5*C6 -> 0 | D8: =Assumptions!$B$11*D5*D6 -> 0
A9: Annual incremental margin | B9: =Assumptions!$B$6*B7 -> 0 | C9: =Assumptions!$B$6*C7 -> 0 | D9: =Assumptions!$B$6*D7 -> 0
A10: Annual net benefit | B10: =B9-B8 -> 0 | C10: =C9-C8 -> 0 | D10: =D9-D8 -> 0
A11: ROI (net benefit / promo cost) | B11: =B10/B8 -> 0 | C11: =C10/C8 -> 0 | D11: =D10/D8 -> 0
A12: Break-even incremental spend / cust / window | B12: =Assumptions!$B$11/Assumptions!$B$6 -> 0 | C12: =Assumptions!$B$11/Assumptions!$B$6 -> 0 | D12: =Assumptions!$B$11/Assumptions!$B$6 -> 0
A13: Break-even eligible lift (% of counterfactual) | B13: =B12/Assumptions!$B$10 -> 0 | C13: =C12/Assumptions!$B$10 -> 0 | D13: =D12/Assumptions!$B$10 -> 0
A14: Scenario eligible lift (% of counterfactual) | B14: =B4/Assumptions!$B$10 -> 0 | C14: =C4/Assumptions!$B$10 -> 0 | D14: =D4/Assumptions!$B$10 -> 0
A15: Memo: annual halo spend (upside) | B15: =Assumptions!$B$15*B5*B6 -> 0 | C15: =Assumptions!$B$15*C5*C6 -> 0 | D15: =Assumptions!$B$15*D5*D6 -> 0
A16: Memo: ROI including halo upside | B16: =(Assumptions!$B$6*(B7+B15)-B8)/B8 -> 0 | C16: =(Assumptions!$B$6*(C7+C15)-C8)/C8 -> 0 | D16: =(Assumptions!$B$6*(D7+D15)-D8)/D8 -> 0
A19: Reading the model
A20: Net benefit > 0 and ROI > 0 mean the promotion pays for itself after cashback cost.
A21: If 'Scenario eligible lift' < 'Break-even eligible lift', that scenario loses money.
A22: Conservative uses the low end of the 95% confidence interval - if it is still positive, the program is robust to statistical uncertainty.
A23: Halo rows show what happens if the (less certain) spillover to other categories holds up.

Sheet Segment Detail (pilot)
A1: Segment | B1: Treated customers | C1: Eligible DiD $/cust | D1: p-value | E1: Significant? | F1: Incr. eligible spend | G1: Halo spend | H1: Promotion cost | I1: Incr. margin | J1: Net benefit | K1: ROI | L1: ROI incl. halo | M1: Break-even lift | N1: Verdict
A2: Affluent Frequent | B2: 920 | C2: 155.73298 | D2: 6.075647e-07 | E2: Yes | F2: 143274.34 | G2: 62447.778 | H2: 25069.24 | I2: 35818.585 | J2: 10749.345 | K2: 0.42878622 | L2: 1.0515392 | M2: 0.14483436 | N2: Significant lift, clearly positive ROI - target / expand
A3: Digital Native | B3: 802 | C3: 81.2262 | D3: 2.0524755e-07 | E3: Yes | F3: 65143.413 | G3: 84127.941 | H3: 9923.67 | I3: 16285.853 | J3: 6362.1832 | K3: 0.64111192 | L3: 2.7604876 | M3: 0.14942611 | N3: Significant lift, clearly positive ROI - target / expand
A4: Mainstream | B4: 1509 | C4: 20.562234 | D4: 0.0087159042 | E4: Yes | F4: 31028.411 | G4: 85507.645 | H4: 10123.63 | I4: 7757.1027 | J4: -2366.5273 | K4: -0.23376272 | L4: 1.8778229 | M4: 0.1321499 | N4: Significant lift but negative ROI at this cashback rate - do not expand
A5: Budget Occasional | B5: 1163 | C5: 5.7519731 | D5: 0.029341655 | E5: Yes | F5: 6689.5447 | G5: -10589.017 | H5: 1858.61 | I5: 1672.3862 | J5: -186.22382 | K5: -0.10019521 | L5: -0.10019521 | M5: 0.1345492 | N5: Significant lift but negative ROI at this cashback rate - do not expand
A6: Dormant Reactivation | B6: 632 | C6: 0.24517179 | D6: 0.92878364 | E6: No | F6: 154.94857 | G6: -12563.262 | H6: 527.75 | I6: 38.737142 | J6: -489.01286 | K6: -0.92659945 | L6: -0.92659945 | M6: 0.12108286 | N6: No statistically reliable lift - cashback would fund inframarginal spend

Sheet Read Me
A1: Merchant Promotion Experimentation Lab - Scenario Model
A3: Purpose: project the annual economics of the cashback promotion from the pilot read.
A5: Sheets:
A6: Assumptions - all inputs (yellow). Change these to test your own assumptions.
A7: Scenario Model - annual cost / revenue / ROI / break-even under 3 scenarios (formula-driven).
A8: Segment Detail (pilot) - measured pilot economics for every segment tested.
A10: Scenario definitions (incremental ELIGIBLE-category spend per customer per window):
A11: Conservative = lower bound of the 95% confidence interval on the difference-in-differences estimate
A12: Base = difference-in-differences point estimate
A13: Upside = upper bound of the 95% confidence interval
A15: Headline ROI is built on eligible-category spend only (the effect the promotion can be
A16: cleanly credited with). Halo spend in other categories is shown as a separate upside.
... A21: Generated by src/build_excel_model.py - re-run the pipeline to refresh.
